README.rst
setup.cfg
setup.py
tgming/__init__.py
tgming/auth.py
tgming/properties.py
tgming.egg-info/PKG-INFO
tgming.egg-info/SOURCES.txt
tgming.egg-info/dependency_links.txt
tgming.egg-info/entry_points.txt
tgming.egg-info/not-zip-safe
tgming.egg-info/requires.txt
tgming.egg-info/top_level.txt