Metadata-Version: 1.1
Name: tgming
Version: 0.0.8
Summary: TurboGears2 Support for Ming MongoDB ORM
Home-page: http://bitbucket.org/_amol_/turbogears-ming
Author: Alessandro Molina
Author-email: alessandro.molina@axant.it
License: MIT
Keywords: turbogears2.extension
Platform: UNKNOWN
Classifier: Environment :: Web Environment
Classifier: Topic :: Software Development :: Libraries :: Python Modules
Classifier: Framework :: TurboGears
